bundestag_protocol_extractor/__init__.py
bundestag_protocol_extractor/__main__.py
bundestag_protocol_extractor/cli.py
bundestag_protocol_extractor/extractor.py
bundestag_protocol_extractor/api/__init__.py
bundestag_protocol_extractor/api/client.py
bundestag_protocol_extractor/models/__init__.py
bundestag_protocol_extractor/models/schema.py
bundestag_protocol_extractor/output/__init__.py
bundestag_protocol_extractor/parsers/__init__.py
bundestag_protocol_extractor/parsers/protocol_parser.py
bundestag_protocol_extractor/parsers/extraction_strategies/__init__.py
bundestag_protocol_extractor/parsers/extraction_strategies/base_strategy.py
bundestag_protocol_extractor/parsers/extraction_strategies/factory.py
bundestag_protocol_extractor/parsers/extraction_strategies/page_strategy.py
bundestag_protocol_extractor/parsers/extraction_strategies/pattern_strategy.py
bundestag_protocol_extractor/parsers/extraction_strategies/xml_strategy.py
bundestag_protocol_extractor/utils/__init__.py
bundestag_protocol_extractor/utils/data_quality.py
bundestag_protocol_extractor/utils/exporter.py
bundestag_protocol_extractor/utils/logging.py
bundestag_protocol_extractor/utils/pandas_helper.py
bundestag_protocol_extractor/utils/progress.py
bundestag_protocol_extractor-0.3.3.dist-info/licenses/LICENSE
bundestag_protocol_extractor-0.3.3.dist-info/METADATA
bundestag_protocol_extractor-0.3.3.dist-info/WHEEL
bundestag_protocol_extractor-0.3.3.dist-info/entry_points.txt
bundestag_protocol_extractor-0.3.3.dist-info/top_level.txt
bundestag_protocol_extractor-0.3.3.dist-info/RECORD
